girokmoji/GITMOJI_LICENSE
girokmoji/__init__.py
girokmoji/__main__.py
girokmoji/catgitmoji.py
girokmoji/changelog.py
girokmoji/const.py
girokmoji/exception.py
girokmoji/git.py
girokmoji/release.py
girokmoji/semver.py
girokmoji/template.py
girokmoji-0.5.19.dist-info/METADATA
girokmoji-0.5.19.dist-info/WHEEL
girokmoji-0.5.19.dist-info/entry_points.txt
girokmoji-0.5.19.dist-info/licenses/LICENSE
girokmoji-0.5.19.dist-info/RECORD
