Metadata-Version: 2.4
Name: girokmoji
Version: 0.5.19
Summary: Change log creator for gitmoji logs
Author-email: Kim Milhan <kimmilhan@gmail.com>
License-File: LICENSE
Keywords: changelog,ci,emoji,git,gitmoji,release,vcs
Classifier: Development Status :: 4 - Beta
Classifier: Intended Audience :: Developers
Classifier: License :: OSI Approved :: GNU General Public License v3 or later (GPLv3+)
Classifier: Operating System :: OS Independent
Classifier: Programming Language :: Python
Classifier: Programming Language :: Python :: 3.10
Classifier: Programming Language :: Python :: 3.11
Classifier: Programming Language :: Python :: 3.12
Classifier: Programming Language :: Python :: 3.13
Classifier: Topic :: Software Development :: Build Tools
Classifier: Topic :: Software Development :: Libraries :: Python Modules
Requires-Python: >=3.10
Requires-Dist: pygit2<2
